dash_aggrid/__init__.py
dash_aggrid_js/AgChartsJS.py
dash_aggrid_js/AgGridJS.py
dash_aggrid_js/VERSION
dash_aggrid_js/__about__.py
dash_aggrid_js/__init__.py
dash_aggrid_js/_imports_.py
dash_aggrid_js/dash_aggrid.min.js
dash_aggrid_js/dash_aggrid.min.js.LICENSE.txt
dash_aggrid_js/dash_aggrid.min.js.map
dash_aggrid_js/dash_aggrid_js.min.js
dash_aggrid_js/dash_aggrid_js.min.js.LICENSE.txt
dash_aggrid_js/dash_aggrid_js.min.js.map
dash_aggrid_js/metadata.json
dash_aggrid_js/package-info.json
dash_aggrid_js/ssrm.py
dash_aggrid_js-0.4.11.dist-info/licenses/LICENSE
dash_aggrid_js-0.4.11.dist-info/METADATA
dash_aggrid_js-0.4.11.dist-info/WHEEL
dash_aggrid_js-0.4.11.dist-info/top_level.txt
dash_aggrid_js-0.4.11.dist-info/RECORD
