Metadata-Version: 2.4
Name: dash-aggrid-js
Version: 0.4.11
Summary: Tiny Dash wrapper that mounts AgGridReact using a JS config registry
Home-page: https://github.com/ScottTpirate/dash-aggrid
Author: Scott Kilgore
Author-email: Scott Kilgore <skilgore@landmarktx.com>
License: MIT
Project-URL: Homepage, https://github.com/ScottTpirate/dash-aggrid
Project-URL: Source, https://github.com/ScottTpirate/dash-aggrid
Project-URL: Tracker, https://github.com/ScottTpirate/dash-aggrid/issues
Classifier: Framework :: Dash
Classifier: License :: OSI Approved :: MIT License
Classifier: Programming Language :: Python :: 3
Classifier: Programming Language :: Python :: 3 :: Only
Requires-Python: >=3.8
License-File: LICENSE
Requires-Dist: dash>=3.1
Provides-Extra: dev
Requires-Dist: pre-commit>=3.6; extra == "dev"
Requires-Dist: build>=1.0; extra == "dev"
Requires-Dist: twine>=4.0; extra == "dev"
Provides-Extra: test
Requires-Dist: pytest>=7.4; extra == "test"
Requires-Dist: dash[testing]>=3.3; extra == "test"
Requires-Dist: selenium<4.3,>=4.1; extra == "test"
Requires-Dist: duckdb<2.0,>=1.4.2; extra == "test"
Dynamic: author
Dynamic: home-page
Dynamic: license-file
Dynamic: requires-python
